.gitignore
.gitkeep
LICENSE
MANIFEST.in
Makefile
README.md
README.rst
convert_md2rst.bat
requirements.txt
setup.py
docs/.gitkeep
docs/how_to_upload_pypi_pkg.md
examples/.gitkeep
examples/sample_annn_pkg_001.html
examples/sample_annn_pkg_001.ipynb
examples/sample_annn_pkg_001.md
sample_annn_pkg/.gitkeep
sample_annn_pkg/__init__.py
sample_annn_pkg/_version.py
sample_annn_pkg/sample_main_module.py
sample_annn_pkg/sample_sub_module.py
sample_annn_pkg.egg-info/PKG-INFO
sample_annn_pkg.egg-info/SOURCES.txt
sample_annn_pkg.egg-info/dependency_links.txt
sample_annn_pkg.egg-info/requires.txt
sample_annn_pkg.egg-info/top_level.txt
sample_annn_pkg/datasets/__init__.py
sample_annn_pkg/datasets/load_datasets.py
sample_annn_pkg/datasets/.gitkeep
sample_annn_pkg/datasets/__init__.py
sample_annn_pkg/datasets/load_datasets.py
sample_annn_pkg/datasets/sample_data/.gitkeep
sample_annn_pkg/datasets/sample_data/sample_data.csv
sample_annn_pkg/datasets/sample_data/sample_data.xlsx
tests/.gitkeep
tests/__init__.py
tests/context.py
tests/test_main_module001.py
tests/test_main_module002.py
tests/test_py_modules.bat