Metadata-Version: 1.0
Name: sample-annn-pkg
Version: 0.0.28
Summary: sample_annn_pkg description
Home-page: https://github.com/laplaciannin102/sample_annn_pkg
Author: hoge
Author-email: fuga@email.com
License: Copyright (c) 2021, laplaciannin102
